<?xml version='1.0' encoding='UTF-8'?>
<package uuid="takeonme-ad1b53">
 <names>
  <name lang="en_US">TakeOnMe</name>
 </names>
 <supportedLanguages>
  <language>en_US</language>
 </supportedLanguages>
 <descriptionLanguages>
  <language>en_US</language>
 </descriptionLanguages>
 <contents>
  <behaviorContent path="behavior_1">
   <nature>interactive</nature>
   <names>
    <name lang="en_US">song</name>
   </names>
   <triggerSentences>
    <sentence lang="en_US">take on me</sentence>
    <sentence lang="en_US">take me on</sentence>
   </triggerSentences>
   <loadingResponses/>
   <autonomous/>
   <permissions/>
  </behaviorContent>
 </contents>
</package>
