<?xml version='1.0' encoding='UTF-8'?>
<package uuid="onthebrightside-8cf24f">
 <names>
  <name lang="en_US">OnTheBrightSide</name>
 </names>
 <supportedLanguages>
  <language>en_US</language>
 </supportedLanguages>
 <descriptionLanguages>
  <language>en_US</language>
 </descriptionLanguages>
 <contents>
  <behaviorContent path="behavior_1">
   <nature>interactive</nature>
   <triggerSentences>
    <sentence lang="en_US">always look at the bright side of life</sentence>
   </triggerSentences>
   <loadingResponses/>
   <autonomous/>
   <permissions/>
  </behaviorContent>
 </contents>
</package>
